TimedInputPy/TimedInputPy.py
TimedInputPy/__init__.py
TimedInputPy-1.0.1.dist-info/METADATA
TimedInputPy-1.0.1.dist-info/WHEEL
TimedInputPy-1.0.1.dist-info/top_level.txt
TimedInputPy-1.0.1.dist-info/RECORD
