Metadata-Version: 2.1
Name: TimedInputPy
Version: 1.0.1
Summary: Implemenation of thread-based timed input object
Author-email: hero24 <hero24@interia.pl>, xenova <None@unknown.org>
Project-URL: Homepage, https://github.com/hero24/TimedInputPy/
Project-URL: Issues, https://github.com/hero24/TimedInputPy/issues/
Classifier: Programming Language :: Python :: 3
Classifier: License :: OSI Approved :: MIT License
Classifier: Operating System :: OS Independent
Requires-Python: >=3.0
